{
  "artifact_type": "codex_exact_record_visual_review_decisions",
  "review_basis": "Each target_zoom was inspected individually; full_context was additionally inspected for ambiguous or initially unclear records.",
  "decisions": [
    {"sample_id":"nude_af577575be6a38ad7030173f","verdict":"reject","reason_code":"wrong_target_or_label","evidence_panels":["target_zoom","full_context"],"review_note":"The annotation is on an abdominal/navel region in a secondary panel, not the canonical anus target."},
    {"sample_id":"nude_eac703ac5362d21b9131d692","verdict":"reject","reason_code":"material_overfill_or_wrong_scale","evidence_panels":["target_zoom"],"review_note":"A coarse square covers the target and substantial neighboring pixels."},
    {"sample_id":"nude_edeec0e67c90c10f6e76f1a8","verdict":"reject","reason_code":"material_overfill_or_wrong_scale","evidence_panels":["target_zoom"],"review_note":"The mask is a coarse region rather than an exact target boundary."},
    {"sample_id":"nude_4d0dbad27311ee4bbae6b19d","verdict":"reject","reason_code":"material_overfill_or_wrong_scale","evidence_panels":["target_zoom"],"review_note":"A rectangular mask includes substantial neighboring perineal anatomy."},
    {"sample_id":"nude_c098fb1b3d5ea34b24ec6c9b","verdict":"reject","reason_code":"material_overfill_or_wrong_scale","evidence_panels":["target_zoom"],"review_note":"An elliptical region materially exceeds the visible target boundary."},
    {"sample_id":"nude_2eff214994c0373bd5896792","verdict":"reject","reason_code":"wrong_target_or_label","evidence_panels":["target_zoom"],"review_note":"The mask follows a broad neighboring genital region rather than the canonical anus target."},
    {"sample_id":"nude_10cd978591cbe11d18653f78","verdict":"reject","reason_code":"material_overfill_or_wrong_scale","evidence_panels":["target_zoom"],"review_note":"A coarse square does not follow the visible target boundary."},
    {"sample_id":"nude_f5031c9419c7577bbd11fb79","verdict":"reject","reason_code":"wrong_target_or_label","evidence_panels":["target_zoom"],"review_note":"The mask is aligned to neighboring external genital anatomy, not an exact anus target."},
    {"sample_id":"nude_b9c5d4aef0cad8ce7aa5289a","verdict":"reject","reason_code":"material_overfill_or_wrong_scale","evidence_panels":["target_zoom"],"review_note":"The rectangle is much larger than the visible target."},
    {"sample_id":"nude_72236c4761978c85ca5559d2","verdict":"reject","reason_code":"material_overfill_or_wrong_scale","evidence_panels":["target_zoom"],"review_note":"A large circular region includes neighboring anatomy."},
    {"sample_id":"nude_fe2eac7007c6eb40c77e5311","verdict":"reject","reason_code":"wrong_target_or_label","evidence_panels":["target_zoom"],"review_note":"The polygon follows a neighboring genital/perineal region rather than an exact anus target."},
    {"sample_id":"nude_568b91df137a0812cdc33ca3","verdict":"reject","reason_code":"material_overfill_or_wrong_scale","evidence_panels":["target_zoom"],"review_note":"A coarse square does not follow the visible target boundary."},
    {"sample_id":"nude_447e9e0889341605381bb78e","verdict":"reject","reason_code":"wrong_target_or_label","evidence_panels":["target_zoom"],"review_note":"The annotation is located on a navel-like target, not the anus."},
    {"sample_id":"nude_9d85380d77a556fc71155cc4","verdict":"reject","reason_code":"material_overfill_or_wrong_scale","evidence_panels":["target_zoom"],"review_note":"The rectangle covers a long intergluteal region rather than the exact target."},
    {"sample_id":"nude_548fc133464a51e4160eb754","verdict":"reject","reason_code":"wrong_target_or_label","evidence_panels":["target_zoom"],"review_note":"The ellipse is centered on the navel, not the anus."},
    {"sample_id":"nude_8f6f3411f92bd0af245fecf8","verdict":"reject","reason_code":"wrong_target_or_label","evidence_panels":["target_zoom"],"review_note":"The mask is on the navel, not the anus."},
    {"sample_id":"nude_9ae73537a137d4da46f19c85","verdict":"reject","reason_code":"wrong_target_or_label","evidence_panels":["target_zoom"],"review_note":"The polygon covers a broad genital/perineal region without an exact anus boundary."},
    {"sample_id":"nude_42bb180ef3abb4bc9d2f86e3","verdict":"reject","reason_code":"wrong_target_or_label","evidence_panels":["target_zoom","full_context"],"review_note":"Full context shows the annotation on a hand/finger region, not the anus."},
    {"sample_id":"nude_ff26efef655cc6bfe466daff","verdict":"reject","reason_code":"wrong_target_or_label","evidence_panels":["target_zoom"],"review_note":"The mask follows a neighboring perineal/genital boundary, not an exact anus target."},
    {"sample_id":"nude_a8dac2e69f77ef78af3114a5","verdict":"reject","reason_code":"material_overfill_or_wrong_scale","evidence_panels":["target_zoom"],"review_note":"A large rectangle materially exceeds the visible target."},
    {"sample_id":"nude_be7bbab36dacc5fb81a1812e","verdict":"reject","reason_code":"material_overfill_or_wrong_scale","evidence_panels":["target_zoom"],"review_note":"A large circular region materially exceeds the visible target."},
    {"sample_id":"nude_eaf4790cd0658a75608983ed","verdict":"abstain","reason_code":"ambiguous_target_scope","evidence_panels":["target_zoom","full_context"],"review_note":"The close-up may depict an anal opening, but the polygon includes a broad perianal ring and the canonical target boundary is not sufficiently resolved for a positive control."},
    {"sample_id":"nude_fac42ba3a28d940f719b5347","verdict":"reject","reason_code":"wrong_target_or_label","evidence_panels":["target_zoom"],"review_note":"The mask follows a neighboring perineal bridge rather than an exact anus target."},
    {"sample_id":"nude_c52186605458fd26b2b225cc","verdict":"reject","reason_code":"wrong_target_or_label","evidence_panels":["target_zoom"],"review_note":"The annotated fold/spot is not an exact canonical anus target."},
    {"sample_id":"nude_2a150d460ee6e186a44e2a6a","verdict":"reject","reason_code":"material_overfill_or_wrong_scale","evidence_panels":["target_zoom"],"review_note":"The rectangle spans the gluteal cleft and neighboring pixels."},
    {"sample_id":"nude_a4647e1e0878b5182bfdb472","verdict":"reject","reason_code":"material_overfill_or_wrong_scale","evidence_panels":["target_zoom"],"review_note":"A large circular region includes multiple neighboring structures."},
    {"sample_id":"nude_13ed130d14d12428b7f5de30","verdict":"reject","reason_code":"wrong_target_or_label","evidence_panels":["target_zoom"],"review_note":"The polygon follows external genital anatomy, not the anus."},
    {"sample_id":"nude_50a6d2cbef015591c70594f8","verdict":"reject","reason_code":"wrong_target_or_label","evidence_panels":["target_zoom"],"review_note":"The mask is aligned to a neighboring genital opening rather than an exact anus target."},
    {"sample_id":"nude_114d66fb061dab61ac3a8501","verdict":"reject","reason_code":"wrong_target_or_label","evidence_panels":["target_zoom"],"review_note":"The annotation is on a navel-like abdominal target, not the anus."},
    {"sample_id":"nude_7eb21ed978c0edd4300b4509","verdict":"reject","reason_code":"material_overfill_or_wrong_scale","evidence_panels":["target_zoom"],"review_note":"The rectangle covers a broad perineal region and does not follow the exact target."},
    {"sample_id":"nude_203c59e999e3b00ec35d82c4","verdict":"reject","reason_code":"material_overfill_or_wrong_scale","evidence_panels":["target_zoom"],"review_note":"A large circular mask materially exceeds the visible target."},
    {"sample_id":"nude_7e5504a47678db424d7f21b7","verdict":"reject","reason_code":"wrong_target_or_label","evidence_panels":["target_zoom"],"review_note":"The polygon covers a broad neighboring genital/perineal region rather than the anus."}
  ]
}
